encoding/G5encode.py
encoding/__init__.py
G5encode-0.0.6.dist-info/LICENSE
G5encode-0.0.6.dist-info/METADATA
G5encode-0.0.6.dist-info/WHEEL
G5encode-0.0.6.dist-info/top_level.txt
G5encode-0.0.6.dist-info/RECORD
