Metadata-Version: 2.1
Name: G5encode
Version: 0.0.6
Summary: This is to encrypt tools or files or words
Home-page: https://github.com/Team-G5/G5encode
Author: Example Author
Author-email: Glitch5@hotmail.com
Project-URL: Bug Tracker, https://github.com/Team-G5/G5encode/issues/1
Classifier: Programming Language :: Python :: 3.7
Classifier: License :: OSI Approved :: MIT License
Classifier: Operating System :: OS Independent
Requires-Python: >=3.6
License-File: LICENSE
